lowsigma/__init__.py
lowsigma/call.py
option_price/__init__.py
option_price/call.py
lowsigma-0.0.5.dist-info/METADATA
lowsigma-0.0.5.dist-info/WHEEL
lowsigma-0.0.5.dist-info/top_level.txt
lowsigma-0.0.5.dist-info/RECORD
