Metadata-Version: 2.1
Name: lowsigma
Version: 0.0.5
Summary: Option Pricing
Home-page: UNKNOWN
Author: UNKNOWN
Author-email: UNKNOWN
License: UNKNOWN
Platform: UNKNOWN
Classifier: Programming Language :: Python :: 3
Classifier: Operating System :: OS Independent
